choicenet/MNL_swissmetro.py
choicenet/__init__.py
choicenet/_nbdev.py
choicenet/core.py
choicenet/pytorch_MNL.py
choicenet/pytorch_discrete_choice.py
choicenet/statsmodels_MNL.py
choicenet/statsmodels_intro.py
choicenet/tastenet_mnl.py
choicenet-0.0.2.dist-info/LICENSE
choicenet-0.0.2.dist-info/METADATA
choicenet-0.0.2.dist-info/WHEEL
choicenet-0.0.2.dist-info/entry_points.txt
choicenet-0.0.2.dist-info/top_level.txt
choicenet-0.0.2.dist-info/RECORD
