Metadata-Version: 2.1
Name: choicenet
Version: 0.0.2
Summary: A library that incoporate discrete choice and deep learning
Home-page: https://github.com/danhphan/choicenet/tree/master/
Author: Danh Phan
Author-email: danhphan@gmail.com
License: Apache Software License 2.0
Keywords: discrete choice,deep learning
Platform: UNKNOWN
Classifier: Development Status :: 3 - Alpha
Classifier: Intended Audience :: Developers
Classifier: License :: OSI Approved :: Apache Software License
Classifier: Natural Language :: English
Classifier: Programming Language :: Python :: 3.6
Classifier: Programming Language :: Python :: 3.7
Classifier: Programming Language :: Python :: 3.8
Requires-Python: >=3.6
